mkdocs_newsletter-1.1.0.dist-info/METADATA
mkdocs_newsletter-1.1.0.dist-info/WHEEL
mkdocs_newsletter-1.1.0.dist-info/entry_points.txt
mkdocs_newsletter-1.1.0.dist-info/licenses/LICENSE
mkdocs_newsletter/__init__.py
mkdocs_newsletter/adapters/__init__.py
mkdocs_newsletter/entrypoints/__init__.py
mkdocs_newsletter/entrypoints/mkdocs_plugin.py
mkdocs_newsletter/model.py
mkdocs_newsletter/py.typed
mkdocs_newsletter/services/__init__.py
mkdocs_newsletter/services/git.py
mkdocs_newsletter/services/nav.py
mkdocs_newsletter/services/newsletter.py
mkdocs_newsletter/services/rss.py
mkdocs_newsletter/templates/marcos.j2
mkdocs_newsletter/templates/newsletter_article.j2
mkdocs_newsletter/templates/newsletter_landing_page.j2
mkdocs_newsletter/templates/rss.xml.j2
mkdocs_newsletter/version.py
mkdocs_newsletter-1.1.0.dist-info/RECORD
