Metadata-Version: 2.1
Name: mkdocs-newsletter
Version: 1.1.0
Summary: Automatically create newsletters from the changes in a mkdocs repository
Home-page: https://github.com/lyz-code/mkdocs-newsletter
Author-Email: Lyz <lyz-code-security-advisories@riseup.net>
License: GPL-3.0-only
Classifier: Development Status :: 5 - Production/Stable
Classifier: Intended Audience :: Developers
Classifier: License :: OSI Approved :: GNU General Public License v3 (GPLv3)
Classifier: Operating System :: Unix
Classifier: Operating System :: POSIX
Classifier: Programming Language :: Python
Classifier: Programming Language :: Python :: 3
Classifier: Programming Language :: Python :: 3.8
Classifier: Programming Language :: Python :: 3.9
Classifier: Programming Language :: Python :: 3.10
Classifier: Programming Language :: Python :: 3.11
Classifier: Topic :: Utilities
Classifier: Natural Language :: English
Project-URL: Issues, https://github.com/lyz-code/mkdocs-newsletter/issues
Project-URL: Homepage, https://github.com/lyz-code/mkdocs-newsletter
Project-URL: Documentation, https://lyz-code.github.io/mkdocs-newsletter
Requires-Python: >=3.8
Requires-Dist: beautifulsoup4>=4.10.0
Requires-Dist: mkdocs>=1.2.3
Requires-Dist: mkdocs-section-index>=0.3.3
Requires-Dist: mkdocs-autolinks-plugin>=0.4.0
Requires-Dist: pydantic<2.0.0
Requires-Dist: gitpython>=3.1.27
Requires-Dist: python-semantic-release>=7.26.0
Requires-Dist: deepdiff>=5.7.0
Requires-Dist: mkdocs-material>=8.2.5
Requires-Dist: mkdocs-git-revision-date-localized-plugin>=1.0.0
